{"digest":"586e676274bc43e4eb55c90ec28c2bb5f0047251","css":"atom-text-editor::shadow .linter-highlight.note:not(.line-number),\n.linter-highlight.note:not(.line-number) {\n  background-color: #0f82e6;\n  color: white;\n}\natom-text-editor::shadow .linter-highlight.note .linter-gutter,\n.linter-highlight.note .linter-gutter {\n  color: #0f82e6;\n}\natom-text-editor::shadow .linter-highlight.note .region,\n.linter-highlight.note .region {\n  border-bottom: 1px dashed #0f82e6;\n}\natom-text-editor::shadow .linter-highlight.help:not(.line-number),\n.linter-highlight.help:not(.line-number) {\n  background-color: #0f82e6;\n  color: white;\n}\natom-text-editor::shadow .linter-highlight.help .linter-gutter,\n.linter-highlight.help .linter-gutter {\n  color: #0f82e6;\n}\natom-text-editor::shadow .linter-highlight.help .region,\n.linter-highlight.help .region {\n  border-bottom: 1px dashed #0f82e6;\n}\natom-text-editor::shadow .linter-highlight.macro:not(.line-number),\n.linter-highlight.macro:not(.line-number) {\n  background-color: #0f82e6;\n  color: white;\n}\natom-text-editor::shadow .linter-highlight.macro .linter-gutter,\n.linter-highlight.macro .linter-gutter {\n  color: #0f82e6;\n}\natom-text-editor::shadow .linter-highlight.macro .region,\n.linter-highlight.macro .region {\n  border-bottom: 1px dashed #0f82e6;\n}\natom-text-editor::shadow .linter-highlight.panic:not(.line-number),\n.linter-highlight.panic:not(.line-number) {\n  background-color: #d13b2e;\n  color: white;\n}\natom-text-editor::shadow .linter-highlight.panic .linter-gutter,\n.linter-highlight.panic .linter-gutter {\n  color: #d13b2e;\n}\natom-text-editor::shadow .linter-highlight.panic .region,\n.linter-highlight.panic .region {\n  border-bottom: 1px dashed #d13b2e;\n}\n","imports":[{"path":"static/variables/ui-variables.less","digest":"e3029f763111ec391f6dcea8178d35be7c798b4f"},{"path":"static/variables/syntax-variables.less","digest":"812c1b7883a023f768773d14294653adcdb932d7"},{"path":"node_modules/one-dark-ui/styles/ui-variables.less","digest":"6f0f0c8b4d99803fc31650b7b5b111f01421959b"},{"path":"node_modules/one-dark-ui/styles/ui-variables-custom.less","digest":"b8334919bfb04e879ed7a083ded0250e4c45dd1a"},{"path":"/home/takaaki/Workspace/Playground/Atom/sepia-plus-syntax/styles/syntax-variables.less","digest":"dd36e8913a3dc3c509bd351e7d3f4ec4e0c11965"},{"path":"/home/takaaki/Workspace/Playground/Atom/sepia-plus-syntax/styles/colors.less","digest":"610758816c17298a66c463f4824976c45b4f1ca0"}],"version":1}